{
  "TRANSFER_CATALOG": {
    "MBJ_AREA": {
      "label": "Montego Bay Area",
      "shuttle": {
        "name": "Shared Transfer: MBJ ↔ Montego Bay Hotels",
        "url": "https://kamartours.com/book/mbj-montego-bay-shared",
        "img": "https://via.placeholder.com/400x250/4A90E2/FFFFFF?text=Tour+Image",
        "fromPrice": 15
      },
      "private": {
        "name": "Private Transfer: MBJ ↔ Montego Bay Hotels",
        "url": "https://kamartours.com/book/mbj-montego-bay-private",
        "img": "https://via.placeholder.com/400x250/4A90E2/FFFFFF?text=Tour+Image",
        "fromPrice": 45
      }
    },
    "OCHO_RIOS": {
      "label": "Ocho Rios",
      "shuttle": {
        "name": "Shared Transfer: MBJ ↔ Ocho Rios",
        "url": "https://kamartours.com/book/mbj-ocho-rios-shared",
        "img": "https://via.placeholder.com/400x250/4A90E2/FFFFFF?text=Tour+Image",
        "fromPrice": 30
      },
      "private": {
        "name": "Private Transfer: MBJ ↔ Ocho Rios",
        "url": "https://kamartours.com/book/mbj-ocho-rios-private",
        "img": "https://via.placeholder.com/400x250/4A90E2/FFFFFF?text=Tour+Image",
        "fromPrice": 85
      }
    },
    "NEGRIL": {
      "label": "Negril",
      "shuttle": {
        "name": "Shared Transfer: MBJ ↔ Negril",
        "url": "https://kamartours.com/book/mbj-negril-shared",
        "img": "https://via.placeholder.com/400x250/4A90E2/FFFFFF?text=Tour+Image",
        "fromPrice": 35
      },
      "private": {
        "name": "Private Transfer: MBJ ↔ Negril",
        "url": "https://kamartours.com/book/mbj-negril-private",
        "img": "https://via.placeholder.com/400x250/4A90E2/FFFFFF?text=Tour+Image",
        "fromPrice": 110
      }
    }
  }
}