{
  "TRANSFER_CATALOG": {
    "MBJ_AREA": {
      "label": "Montego Bay Area",
      "shuttle": {
        "name": "Shuttle Transportation: MBJ ↔ Montego Bay Area",
        "url": "/airport-transfer-sangster-to-montego-bay-shuttle",
        "img": "/demo/images/tour-image.jpeg",
        "fromPrice": 12
      },
      "private": {
        "name": "Private Transportation: MBJ ↔ Montego Bay Area",
        "url": "/airport-transfer-sangster-to-montego-bay-private",
        "img": "/demo/images/tour-image.jpeg",
        "fromPrice": 35
      }
    },
    "OCHO_RIOS": {
      "label": "Ocho Rios",
      "shuttle": { "name": "Shuttle: MBJ ↔ Ocho Rios", "url": "/airport-transfer-sangster-to-ocho-rios-shuttle", "img": "/demo/images/tour-image.jpeg", "fromPrice": 25 },
      "private": { "name": "Private: MBJ ↔ Ocho Rios", "url": "/airport-transfer-sangster-to-ocho-rios-private", "img": "/demo/images/tour-image.jpeg", "fromPrice": 80 }
    },
    "NEGRIL": {
      "label": "Negril",
      "shuttle": { "name": "Shuttle: MBJ ↔ Negril", "url": "/airport-transfer-sangster-to-negril-shuttle", "img": "/demo/images/tour-image.jpeg", "fromPrice": 28 },
      "private": { "name": "Private: MBJ ↔ Negril", "url": "/airport-transfer-sangster-to-negril-private", "img": "/demo/images/tour-image.jpeg", "fromPrice": 95 }
    }
  }
}